aito/__init__.py
aito/aicalm/agents/__init__.py
aito/aicalm/agents/time_series_analyzer/__init__.py
aito/img_classif/__init__.py
aito/img_classif/imagenet.py
aito/img_classif/util.py
aito/iot_mgmt/api.py
aito/iot_mgmt/utils.py
aito/iot_mgmt/data/admin.py
aito/iot_mgmt/data/apps.py
aito/iot_mgmt/data/filters.py
aito/iot_mgmt/data/models.py
aito/iot_mgmt/data/querysets.py
aito/iot_mgmt/data/serializers.py
aito/iot_mgmt/data/urls.py
aito/iot_mgmt/data/views.py
aito/iot_mgmt/data/migrations/0001_initial.py
aito/iot_mgmt/data/migrations/0002_equipmentuniquetype_data_fields.py
aito/iot_mgmt/data/migrations/0003_equipmentinstance.py
aito/iot_mgmt/data/migrations/0004_auto_20180103_1007.py
aito/iot_mgmt/data/migrations/0005_auto_20180103_1059.py
aito/iot_mgmt/data/migrations/0006_auto_20180410_1904.py
aito/iot_mgmt/data/migrations/0007_auto_20180703_1156.py
aito/iot_mgmt/data/migrations/0008_equipmentinstanceassociation.py
aito/iot_mgmt/data/migrations/0009_auto_20180724_2039.py
aito/iot_mgmt/data/migrations/0010_auto_20180803_0015.py
aito/iot_mgmt/data/migrations/0011_auto_20180803_0024.py
aito/iot_mgmt/data/migrations/0012_auto_20180803_0033.py
aito/iot_mgmt/data/migrations/0013_auto_20180803_1030.py
aito/iot_mgmt/data/migrations/0014_auto_20180803_1031.py
aito/iot_mgmt/data/migrations/0015_equipmentuniquetypegroup_equipment_data_fields.py
aito/iot_mgmt/data/migrations/0016_auto_20180908_1532.py
aito/iot_mgmt/data/migrations/0017_auto_20180909_0502.py
aito/iot_mgmt/data/migrations/0018_auto_20180926_1510.py
aito/iot_mgmt/data/migrations/0019_auto_20181002_1415.py
aito/iot_mgmt/data/migrations/0020_remove_equipmentdatafield_nullable.py
aito/iot_mgmt/data/migrations/0021_auto_20181025_0733.py
aito/iot_mgmt/data/migrations/0022_equipmentinstancedatafielddailyaggregate.py
aito/iot_mgmt/data/migrations/0023_auto_20181110_0727.py
aito/iot_mgmt/data/migrations/0024_auto_20181110_1840.py
aito/iot_mgmt/data/migrations/0025_auto_20181110_1850.py
Aitomatic_Contrib-23.11.26.dist-info/LICENSE
Aitomatic_Contrib-23.11.26.dist-info/METADATA
Aitomatic_Contrib-23.11.26.dist-info/WHEEL
Aitomatic_Contrib-23.11.26.dist-info/entry_points.txt
Aitomatic_Contrib-23.11.26.dist-info/top_level.txt
Aitomatic_Contrib-23.11.26.dist-info/zip-safe
Aitomatic_Contrib-23.11.26.dist-info/RECORD
