Metadata-Version: 2.1
Name: Aitomatic-Contrib
Version: 23.11.26
Summary: Aitomatic Contrib
Author-email: "Aitomatic, Inc." <engineering@aitomatic.com>
Maintainer-email: "Aitomatic, Inc." <engineering@aitomatic.com>
License: Apache License
Project-URL: Homepage, https://GitHub.com/Aitomatic/Contrib
Project-URL: Repository, https://GitHub.com/Aitomatic/Contrib
Project-URL: GitHub, https://GitHub.com/Aitomatic/Contrib
Project-URL: Documentation, https://GitHub.com/Aitomatic/Contrib
Keywords: Aitomatic,contrib
Requires-Python: >=3.11
License-File: LICENSE
Requires-Dist: Pandas >=1.5
Requires-Dist: PyArrow >=14.0.1
Requires-Dist: PySpark >=3.5.0
Requires-Dist: Pillow >=9.5
Requires-Dist: PyCOCOTools >=2.0.7
Requires-Dist: Imbalanced-Learn >=0.11.0
Requires-Dist: TensorFlow >=2.15.0
Requires-Dist: Transformers >=4.35.2
Requires-Dist: LangChain >=0.0.340
Requires-Dist: Django >=4.2.7
Requires-Dist: Django-Configurations >=2.5
Requires-Dist: Django-CORS-Headers >=4.3.1
Requires-Dist: Django-Environ >=0.11.2
Requires-Dist: Django-Extensions >=3.2.3
Requires-Dist: Django-Jazzmin >=2.6.0
Requires-Dist: DjangoRESTFramework >=3.14.0
Requires-Dist: Django-Silk >=5.0.4
Requires-Dist: DRF-Writable-Nested >=0.7.0
Requires-Dist: PsycoPG >=3.1.13
Requires-Dist: PsycoPG2-binary >=2.9.9
Requires-Dist: OpenSSA-dev[cv] >=0.1.6.2
Requires-Dist: CLICK >=8.1.7
Requires-Dist: Python-DotEnv >=1.0.0
Requires-Dist: Ruamel.YAML >=0.18.5
Provides-Extra: build
Requires-Dist: Build >=1.0.3 ; extra == 'build'
Provides-Extra: dev
Requires-Dist: Commitizen >=3.12.0 ; extra == 'dev'
Requires-Dist: Pre-Commit >=3.5.0 ; extra == 'dev'
Requires-Dist: PyWatchman >=1.4.1 ; extra == 'dev'
Provides-Extra: doc
Requires-Dist: Sphinx >=7.2.6 ; extra == 'doc'
Requires-Dist: Sphinx-AutoBuild >=2021.3.14 ; extra == 'doc'
Requires-Dist: SphinxContrib-JSMath >=1.0.1 ; extra == 'doc'
Requires-Dist: CommonMark >=0.9.1 ; extra == 'doc'
Requires-Dist: ReCommonMark >=0.7.1 ; extra == 'doc'
Provides-Extra: lint
Requires-Dist: Bandit >=1.7.5 ; extra == 'lint'
Requires-Dist: Flake8 >=6.1.0 ; extra == 'lint'
Requires-Dist: MyPy >=1.7.1 ; extra == 'lint'
Requires-Dist: PyCodeStyle >=2.11.1 ; extra == 'lint'
Requires-Dist: PyDocStyle[toml] >=6.3.0 ; extra == 'lint'
Requires-Dist: PyLama >=8.4.1 ; extra == 'lint'
Requires-Dist: PyLint >=3.0.2 ; extra == 'lint'
Requires-Dist: ReactPy-Flake8 >=0.7.0 ; extra == 'lint'
Provides-Extra: publish
Requires-Dist: Twine >=4.0.2 ; extra == 'publish'
Provides-Extra: test
Requires-Dist: Nose >=1.3.7 ; extra == 'test'
Requires-Dist: Nose2 >=0.14.0 ; extra == 'test'
Requires-Dist: PyTest >=7.4.3 ; extra == 'test'
Requires-Dist: PyTest-Cov >=4.1.0 ; extra == 'test'
Requires-Dist: UnitTest2 >=1.1.0 ; extra == 'test'
